ucamprojectlight/__init__.py
ucamprojectlight/static/images/interface/bg-blockquote-bottom.png
ucamprojectlight/static/images/interface/bg-blockquote-top.png
ucamprojectlight/static/images/interface/bg-breadcrumb-link.png
ucamprojectlight/static/images/interface/bg-carousel-caption.png
ucamprojectlight/static/images/interface/bg-download-arrow.png
ucamprojectlight/static/images/interface/bg-footer-navigation.png
ucamprojectlight/static/images/interface/bg-local-navigation-back-arrow.png
ucamprojectlight/static/images/interface/bg-local-navigation-sub-arrow.png
ucamprojectlight/static/images/interface/bg-mobile-nav-border.png
ucamprojectlight/static/images/interface/bg-nav-arrow.png
ucamprojectlight/static/images/interface/bg-navigation-divider.png
ucamprojectlight/static/images/interface/bg-primary-cta-arrow-over.png
ucamprojectlight/static/images/interface/bg-primary-cta-arrow.png
ucamprojectlight/static/images/interface/bg-secondary-cta-arrow.png
ucamprojectlight/static/images/interface/bg-vertical-breadcrumb-indicator-arrow-over.png
ucamprojectlight/static/images/interface/bg-vertical-breadcrumb-indicator-arrow.png
ucamprojectlight/static/images/interface/bg-vertical-breadcrumb-right-arrow.png
ucamprojectlight/static/images/interface/bg-vertical-breadcrumb-up-arrow.png
ucamprojectlight/static/images/interface/bg_list_indicator.png
ucamprojectlight/static/images/interface/btn-carousel-next-disabled.png
ucamprojectlight/static/images/interface/btn-carousel-next.png
ucamprojectlight/static/images/interface/btn-carousel-prev-disabled.png
ucamprojectlight/static/images/interface/btn-carousel-prev.png
ucamprojectlight/static/images/interface/btn-close-panel.png
ucamprojectlight/static/images/interface/btn-download-vcard.png
ucamprojectlight/static/images/interface/btn-mobile-nav-menu-closed.png
ucamprojectlight/static/images/interface/btn-mobile-nav-menu.png
ucamprojectlight/static/images/interface/btn-open-menu-sprite.png
django_ucamprojectlight-1.2.1.dist-info/AUTHORS
django_ucamprojectlight-1.2.1.dist-info/LICENSE
django_ucamprojectlight-1.2.1.dist-info/METADATA
django_ucamprojectlight-1.2.1.dist-info/WHEEL
django_ucamprojectlight-1.2.1.dist-info/top_level.txt
django_ucamprojectlight-1.2.1.dist-info/RECORD
