Metadata-Version: 2.1
Name: django-ucamprojectlight
Version: 1.2.1
Summary: A Django module to use the template system of the University of Cambridge: Project light
Home-page: https://github.com/uisautomation/django-ucamprojectlight.git
Author: University of Cambridge
Author-email: information-systems@ucs.cam.ac.uk
License: MIT
Classifier: Development Status :: 5 - Production/Stable
Classifier: Environment :: Web Environment
Classifier: Framework :: Django
Classifier: Intended Audience :: Developers
Classifier: License :: OSI Approved :: MIT License
Classifier: Operating System :: OS Independent
Classifier: Programming Language :: Python
License-File: LICENSE
License-File: AUTHORS
